gantt_project_maker/__init__.py
gantt_project_maker/colors.py
gantt_project_maker/excelwriter.py
gantt_project_maker/gantt.py
gantt_project_maker/main.py
gantt_project_maker/project_classes.py
gantt_project_maker/utils.py
gantt_project_maker-0.4.4.dist-info/LICENSE.txt
gantt_project_maker-0.4.4.dist-info/METADATA
gantt_project_maker-0.4.4.dist-info/WHEEL
gantt_project_maker-0.4.4.dist-info/entry_points.txt
gantt_project_maker-0.4.4.dist-info/top_level.txt
gantt_project_maker-0.4.4.dist-info/RECORD
