Metadata-Version: 2.1
Name: gantt-project-maker
Version: 0.4.4
Summary: Create Gantt project charts
Home-page: https://github.com/eelcovv/gantt-project-maker/
Author: Eelco van Vliet
Author-email: eelcovv@gmail.com
License: MIT
Project-URL: Documentation, https://gantt-project-maker.readthedocs.io/en/latest/
Platform: any
Classifier: Development Status :: 4 - Beta
Classifier: Programming Language :: Python
License-File: LICENSE.txt
Requires-Dist: pandas
Requires-Dist: python-dateutil
Requires-Dist: PyYAML
Requires-Dist: SVG42PDF
Requires-Dist: svgwrite
Requires-Dist: webcolors
Requires-Dist: xlsxWriter
Requires-Dist: importlib-metadata ; python_version < "3.8"
Provides-Extra: dev
Requires-Dist: pre-commit ; extra == 'dev'
Requires-Dist: pytest ; extra == 'dev'
Requires-Dist: pytest-cov ; extra == 'dev'
Requires-Dist: setuptools <=69.2.0 ; extra == 'dev'
Requires-Dist: sphinx >=3.2.1 ; extra == 'dev'
Requires-Dist: sphinx-rtd-theme ; extra == 'dev'
Requires-Dist: importlib-metadata ; (python_version < "3.8") and extra == 'dev'
Provides-Extra: testing
Requires-Dist: setuptools ; extra == 'testing'
Requires-Dist: pytest ; extra == 'testing'
Requires-Dist: pytest-cov ; extra == 'testing'
